mrra/__init__.py
mrra/config.py
mrra/agents/__init__.py
mrra/agents/builder.py
mrra/agents/reflection.py
mrra/agents/subagents.py
mrra/analysis/activity_purpose.py
mrra/data/__init__.py
mrra/data/activity.py
mrra/data/trajectory.py
mrra/graph/__init__.py
mrra/graph/mobility_graph.py
mrra/graph/pattern.py
mrra/persist/cache.py
mrra/retriever/__init__.py
mrra/retriever/graph_rag.py
mrra/tools/__init__.py
mrra/tools/mcp_gmap.py
mrra/tools/mcp_maps.py
mrra/tools/mcp_weather.py
mrra/utils/geo.py
mrra-0.1.3.dist-info/licenses/LICENSE
mrra-0.1.3.dist-info/METADATA
mrra-0.1.3.dist-info/WHEEL
mrra-0.1.3.dist-info/top_level.txt
mrra-0.1.3.dist-info/RECORD
