Metadata-Version: 2.4
Name: mrra
Version: 0.1.3
Summary: Mobility Retrieve-and-Reflect Agent: GraphRAG + Multi-Agent Reflection for mobility trajectories
Author-email: Ao Wang <2331623@tongji.edu.cn>
License-Expression: MIT
Project-URL: Homepage, https://www.mrra.tech/
Project-URL: Repository, https://github.com/AoWangg/mrra
Project-URL: Issues, https://github.com/AoWangg/mrra/issues
Project-URL: Documentation, https://www.mrra.tech/en/docs
Keywords: mobility,trajectory,graph,rag,agent,prediction,langchain,mcp
Classifier: Development Status :: 3 - Alpha
Classifier: Intended Audience :: Science/Research
Classifier: Intended Audience :: Developers
Classifier: Operating System :: OS Independent
Classifier: Programming Language :: Python :: 3
Classifier: Programming Language :: Python :: 3.10
Classifier: Programming Language :: Python :: 3.11
Classifier: Programming Language :: Python :: 3.12
Classifier: Topic :: Scientific/Engineering :: Artificial Intelligence
Classifier: Topic :: Software Development :: Libraries :: Python Modules
Requires-Python: >=3.10
License-File: LICENSE
Requires-Dist: pandas>=2.0
Requires-Dist: numpy>=1.24
Requires-Dist: networkx>=3.1
Requires-Dist: pydantic>=2
Requires-Dist: typing-extensions>=4.8
Requires-Dist: langchain-core>=0.2.26
Requires-Dist: langchain-openai>=0.2.0
Requires-Dist: httpx[socks]>=0.24.0
Provides-Extra: dev
Requires-Dist: pytest>=7; extra == "dev"
Requires-Dist: ruff>=0.5.0; extra == "dev"
Provides-Extra: mcp
Requires-Dist: langchain-mcp-adapters>=0.1.0; extra == "mcp"
Requires-Dist: mcp>=1.0; extra == "mcp"
Requires-Dist: httpx-sse>=0.4; extra == "mcp"
Requires-Dist: anyio>=4.5; extra == "mcp"
Dynamic: license-file
